phoebe_bird/__init__.py
phoebe_bird/_base_client.py
phoebe_bird/_client.py
phoebe_bird/_compat.py
phoebe_bird/_constants.py
phoebe_bird/_exceptions.py
phoebe_bird/_files.py
phoebe_bird/_models.py
phoebe_bird/_qs.py
phoebe_bird/_resource.py
phoebe_bird/_response.py
phoebe_bird/_streaming.py
phoebe_bird/_types.py
phoebe_bird/_version.py
phoebe_bird/py.typed
phoebe_bird/_utils/__init__.py
phoebe_bird/_utils/_compat.py
phoebe_bird/_utils/_datetime_parse.py
phoebe_bird/_utils/_logs.py
phoebe_bird/_utils/_proxy.py
phoebe_bird/_utils/_reflection.py
phoebe_bird/_utils/_resources_proxy.py
phoebe_bird/_utils/_streams.py
phoebe_bird/_utils/_sync.py
phoebe_bird/_utils/_transform.py
phoebe_bird/_utils/_typing.py
phoebe_bird/_utils/_utils.py
phoebe_bird/lib/.keep
phoebe_bird/resources/__init__.py
phoebe_bird/resources/data/__init__.py
phoebe_bird/resources/data/data.py
phoebe_bird/resources/data/observations/__init__.py
phoebe_bird/resources/data/observations/observations.py
phoebe_bird/resources/data/observations/geo/__init__.py
phoebe_bird/resources/data/observations/geo/geo.py
phoebe_bird/resources/data/observations/geo/recent/__init__.py
phoebe_bird/resources/data/observations/geo/recent/notable.py
phoebe_bird/resources/data/observations/geo/recent/recent.py
phoebe_bird/resources/data/observations/geo/recent/species.py
phoebe_bird/resources/data/observations/nearest/__init__.py
phoebe_bird/resources/data/observations/nearest/geo_species.py
phoebe_bird/resources/data/observations/nearest/nearest.py
phoebe_bird/resources/data/observations/recent/__init__.py
phoebe_bird/resources/data/observations/recent/historic.py
phoebe_bird/resources/data/observations/recent/notable.py
phoebe_bird/resources/data/observations/recent/recent.py
phoebe_bird/resources/data/observations/recent/species.py
phoebe_bird/resources/product/__init__.py
phoebe_bird/resources/product/checklist.py
phoebe_bird/resources/product/product.py
phoebe_bird/resources/product/species_list.py
phoebe_bird-0.1.0a11.dist-info/METADATA
phoebe_bird-0.1.0a11.dist-info/WHEEL
phoebe_bird-0.1.0a11.dist-info/licenses/LICENSE
phoebe_bird-0.1.0a11.dist-info/RECORD
